pyrlutils/__init__.py
pyrlutils/action.py
pyrlutils/policy.py
pyrlutils/reward.py
pyrlutils/state.py
pyrlutils/transition.py
pyrlutils/bandit/__init__.py
pyrlutils/bandit/algo.py
pyrlutils/bandit/reward.py
pyrlutils/dp/__init__.py
pyrlutils/dp/valuefcns.py
pyrlutils/helpers/__init__.py
pyrlutils/helpers/exceptions.py
pyrlutils/openai/__init__.py
pyrlutils/openai/utils.py
pyrlutils/td/__init__.py
pyrlutils/td/doubleqlearn.py
pyrlutils/td/qlearn.py
pyrlutils/td/sarsa.py
pyrlutils/td/state_td.py
pyrlutils/td/utils.py
pyrlutils-0.1.2.dist-info/licenses/LICENSE
pyrlutils-0.1.2.dist-info/METADATA
pyrlutils-0.1.2.dist-info/WHEEL
pyrlutils-0.1.2.dist-info/top_level.txt
pyrlutils-0.1.2.dist-info/RECORD
