Metadata-Version: 2.4
Name: pyrlutils
Version: 0.1.2
Summary: Utility and Helpers for Reinformcement Learning
Author-email: Kwan Yuet Stephen Ho <stephenhky@yahoo.com.hk>
License: MIT
Project-URL: Repository, https://github.com/stephenhky/PyRLUtils
Project-URL: Issues, https://github.com/stephenhky/PyRLUtils/issues
Keywords: machine learning,reinforcement leaning,artificial intelligence
Classifier: Topic :: Scientific/Engineering :: Mathematics
Classifier: License :: OSI Approved :: MIT License
Classifier: Topic :: Software Development :: Libraries :: Python Modules
Classifier: Topic :: Software Development :: Version Control :: Git
Classifier: Programming Language :: Python :: 3.10
Classifier: Programming Language :: Python :: 3.11
Classifier: Programming Language :: Python :: 3.12
Classifier: Programming Language :: Python :: 3.13
Classifier: Intended Audience :: Science/Research
Classifier: Intended Audience :: Developers
Requires-Python: >=3.10
License-File: LICENSE
Requires-Dist: numpy
Requires-Dist: npdict>=0.0.7
Requires-Dist: typing-extensions
Provides-Extra: openaigym
Requires-Dist: gymnasium; extra == "openaigym"
Provides-Extra: test
Requires-Dist: unittest; extra == "test"
Dynamic: license-file
